gcpath/__init__.py
gcpath/cli.py
gcpath/core.py
gcpath/formatters.py
gcpath/loaders.py
gcpath/parsers.py
gcpath-0.2.3.dist-info/METADATA
gcpath-0.2.3.dist-info/WHEEL
gcpath-0.2.3.dist-info/entry_points.txt
gcpath-0.2.3.dist-info/licenses/LICENSE
gcpath-0.2.3.dist-info/RECORD
