Metadata-Version: 2.4
Name: gcpath
Version: 0.2.3
Summary: A CLI utility to manage Google Cloud Platform resource hierarchy paths.
Project-URL: Homepage, https://github.com/tardigrde/gcpath
Project-URL: Repository, https://github.com/tardigrde/gcpath
Project-URL: Issues, https://github.com/tardigrde/gcpath/issues
Author-email: Levente <leventetsk@proton.me>
License-File: LICENSE
Keywords: folders,gcp,google-cloud,hierarchy,projects
Classifier: Development Status :: 4 - Beta
Classifier: Environment :: Console
Classifier: Intended Audience :: Developers
Classifier: Intended Audience :: System Administrators
Classifier: License :: OSI Approved :: MIT License
Classifier: Programming Language :: Python :: 3.12
Classifier: Topic :: Utilities
Requires-Python: >=3.12
Requires-Dist: google-cloud-asset>=4.1.0
Requires-Dist: google-cloud-resource-manager>=1.15.0
Requires-Dist: rich>=14.2.0
Requires-Dist: typer>=0.20.1
